practice/dff.v
// ===================================================
//	=================[ VLSISYS Lab. ]=================
//	* Author		: oksj (oksj@sookmyung.ac.kr)
//	* Filename		: dff.v
//	* Date			: 2025-03-05 
//	* Description	: 
// ===================================================


module dff
(
	output				o_q,
	input				i_d,
	input				i_clk,
	input				i_rstn
);

	reg	q_internal;

	always @(posedge i_clk or negedge i_rstn) begin
		if(!i_rstn) begin
			q_internal	<= 0;
		end else begin
			q_internal	<= i_d;
		end
	end

	buf	#(3) (o_q, q_internal);

	/*wire	r0, s0;
	wire	q0, q_0;

	nand	#(3)(s0, i_d, i_clk);
	nand	#(3)(r0, s0,i_clk);
	nand	#(3)(q0,q_0, s0);
	nand	#(3)(q_0, q0, r0);

	wire	n_clk;
	wire	r1, s1, q1, q_1;

	not		#(3)(n_clk, i_clk);
	nand	#(3)(s1, q0, n_clk);
	nand	#(3)(r1, s1, n_clk);
	nand	#(3)(q1, q_1,s1);
	nand	#(3)(q_1, q1, r1);

	assign	o_q = q1;
*/
endmodule

practice/click.v
// ===================================================
//	=================[ VLSISYS Lab. ]=================
//	* Author		: oksj (oksj@sookmyung.ac.kr)
//	* Filename		: click.v
//	* Date			: 2025-03-05 
//	* Description	: 
// ===================================================
`include		"dff.v"

module click 
(
	output		o_click,
	output		o_reqR,
	output		o_ackL,
	input 		i_reqL,
	input 		i_ackR,

	input 		i_rstn
);


	wire		xor_out, xnor_out, and_out;
	wire		dff_outL, dff_outR;

	xor		#(6)(xor_out, i_reqL, dff_outL);
	xnor	#(9)(xnor_out, dff_outR, i_ackR);
	and		#(4)(and_out, xor_out, xnor_out);

	wire		n_dff_outL, n_dff_outR;
	not		#(3)(n_dff_outL, dff_outL);
	not		#(3)(n_dff_outR, dff_outR);

	dff
	u_dffL(
		.o_q	(dff_outL	),
		.i_d	(n_dff_outL	),
		.i_clk	(and_out	),
		.i_rstn	(i_rstn		)
	);
	
	dff
	u_dffR(
		.o_q	(dff_outR	),
		.i_d	(n_dff_outR	),
		.i_clk	(and_out	),
		.i_rstn	(i_rstn		)
	);

	assign		o_click	= and_out;
	assign		o_reqR	= dff_outR;
	assign		o_ackL	= dff_outL;
	
endmodule

practice/click_tb.v
// ===================================================
//	=================[ VLSISYS Lab. ]=================
//	* Author		: oksj (oksj@sookmyung.ac.kr)
//	* Filename		: click_tb.v
//	* Date			: 2025-03-05 
//	* Description	: 
// ===================================================
// --------------------------------------------------
//	Define Global Variables
// --------------------------------------------------
`define	CLKFREQ		100		// Clock Freq. (Unit: MHz)
`define	SIMCYCLE	`NVEC	// Sim. Cycles
`define NVEC		100		// # of Test Vector

// --------------------------------------------------
//	Includes
// --------------------------------------------------
`include	"click.v"

module click_tb;
// --------------------------------------------------
//	DUT Signals & Instantiate
// --------------------------------------------------
	wire		o_click;
	wire		o_ackL;
	wire		o_reqR;


	reg			i_reqL;
	reg 		i_ackR;
	reg			i_rstn;

	click
	u_click1(
		.o_click			(o_click			),
		.o_reqR				(o_reqR				),
		.o_ackL				(o_ackL				),
		.i_reqL				(i_reqL				),
		.i_ackR				(i_ackR				),
		.i_rstn				(i_rstn				)
	);

	always @(*) begin
		if(o_reqR) i_ackR=1;
	end
// --------------------------------------------------
//	Test Stimulus
// --------------------------------------------------
	integer		i, j;
	initial begin
		i_reqL=0;
		i_ackR=0;
		i_rstn=0;

		#(50);
		i_rstn=1;

		
		i_reqL=0;

		#(30);
		i_reqL=1;

		#(30);
		i_reqL=0;

		i_ackR=1;
		#(30);

		i_ackR=0;
		#(30);
		$finish;
	end

// --------------------------------------------------
//	Dump VCD
// --------------------------------------------------
	reg	[8*32-1:0]	vcd_file;
	initial begin
		if ($value$plusargs("vcd_file=%s", vcd_file)) begin
			$dumpfile(vcd_file);
			$dumpvars;
		end else begin
			$dumpfile("click_tb.vcd");
			$dumpvars;
		end
	end

endmodule

practice/vcd/click.vcd
$date
	Wed Mar  5 21:34:04 2025
$end
$version
	Icarus Verilog
$end
$timescale
	1ps
$end
$scope module click_tb $end
$var wire 1 ! o_reqR $end
$var wire 1 " o_click $end
$var wire 1 # o_ackL $end
$var reg 1 $ i_ackR $end
$var reg 1 % i_reqL $end
$var reg 1 & i_rstn $end
$var reg 256 ' vcd_file [255:0] $end
$scope module u_click1 $end
$var wire 1 ( and_out $end
$var wire 1 $ i_ackR $end
$var wire 1 % i_reqL $end
$var wire 1 & i_rstn $end
$var wire 1 ) n_dff_outL $end
$var wire 1 * n_dff_outR $end
$var wire 1 # o_ackL $end
$var wire 1 " o_click $end
$var wire 1 ! o_reqR $end
$var wire 1 + xnor_out $end
$var wire 1 , xor_out $end
$var wire 1 - dff_outR $end
$var wire 1 . dff_outL $end
$scope module u_dffL $end
$var wire 1 ( i_clk $end
$var wire 1 ) i_d $end
$var wire 1 & i_rstn $end
$var wire 1 . o_q $end
$var reg 1 / q_internal $end
$upscope $end
$scope module u_dffR $end
$var wire 1 ( i_clk $end
$var wire 1 * i_d $end
$var wire 1 & i_rstn $end
$var wire 1 - o_q $end
$var reg 1 0 q_internal $end
$upscope $end
$upscope $end
$upscope $end
$enddefinitions $end
#0
$dumpvars
00
0/
x.
x-
x,
x+
x*
x)
x(
b1011100010111101110110011000110110010000101111011000110110110001101001011000110110101100101110011101100110001101100100 '
0&
0%
0$
x#
x"
x!
$end
#3000
0#
0.
0!
0-
#6000
1)
1*
#9000
0,
#12000
1+
#13000
0"
0(
#50000
1&
#80000
1%
#86000
1,
#90000
10
1/
1"
1(
#93000
1$
1!
1-
1#
1.
#96000
0*
0)
#99000
0,
#103000
0"
0(
#110000
0%
#116000
1,
#120000
0/
00
1"
1(
#123000
0#
0.
0!
0-
#126000
1)
1*
#129000
0,
#132000
0+
#133000
0"
0(
#140000
0$
#149000
1+
