practice/dff.v
// ===================================================
//	=================[ VLSISYS Lab. ]=================
//	* Author		: oksj (oksj@sookmyung.ac.kr)
//	* Filename		: dff.v
//	* Date			: 2025-03-05 
//	* Description	: 
// ===================================================


module dff
(
	output				o_q,
	input				i_d,
	input				i_clk,
	input				i_rstn
);

	reg	q_internal;

	always @(posedge i_clk or negedge i_rstn) begin
		if(!i_rstn) begin
			q_internal	<= 0;
		end else begin
			q_internal	<= i_d;
		end
	end

	buf	#(3) (o_q, q_internal);

	/*wire	r0, s0;
	wire	q0, q_0;

	nand	#(3)(s0, i_d, i_clk);
	nand	#(3)(r0, s0,i_clk);
	nand	#(3)(q0,q_0, s0);
	nand	#(3)(q_0, q0, r0);

	wire	n_clk;
	wire	r1, s1, q1, q_1;

	not		#(3)(n_clk, i_clk);
	nand	#(3)(s1, q0, n_clk);
	nand	#(3)(r1, s1, n_clk);
	nand	#(3)(q1, q_1,s1);
	nand	#(3)(q_1, q1, r1);

	assign	o_q = q1;
*/
endmodule

practice/click.v
// ===================================================
//	=================[ VLSISYS Lab. ]=================
//	* Author		: oksj (oksj@sookmyung.ac.kr)
//	* Filename		: click.v
//	* Date			: 2025-03-05 
//	* Description	: 
// ===================================================
`include		"dff.v"

module click 
(
	output		o_click,
	output		o_reqR,
	output		o_ackL,
	input 		i_reqL,
	input 		i_ackR,

	input 		i_rstn
);


	wire		xor_out, xnor_out, and_out;
	wire		dff_outL, dff_outR;

	xor		#(6)(xor_out, i_reqL, dff_outL);
	xnor	#(9)(xnor_out, dff_outR, i_ackR);
	and		#(4)(and_out, xor_out, xnor_out);

	wire		n_dff_outL, n_dff_outR;
	not		#(3)(n_dff_outL, dff_outL);
	not		#(3)(n_dff_outR, dff_outR);

	dff
	u_dffL(
		.o_q	(dff_outL	),
		.i_d	(n_dff_outL	),
		.i_clk	(and_out	),
		.i_rstn	(i_rstn		)
	);
	
	dff
	u_dffR(
		.o_q	(dff_outR	),
		.i_d	(n_dff_outR	),
		.i_clk	(and_out	),
		.i_rstn	(i_rstn		)
	);

	assign		o_click	= and_out;
	assign		o_reqR	= dff_outR;
	assign		o_ackL	= dff_outL;
	
endmodule

practice/fsm.v
// ===================================================
//	=================[ VLSISYS Lab. ]=================
//	* Author		: oksj (oksj@sookmyung.ac.kr)
//	* Filename		: fsm.v
//	* Date			: 2025-03-05 
//	* Description	: 
// ===================================================
`include	"click.v"

module fsm
(
	output			[1:0]	o_light_a,
	output			[1:0]	o_light_b,
	input					i_traffic_a,
	input					i_traffic_b,
	input					i_mode_p,
	input					i_mode_r,
	input					i_rstn,
	output					o_reqR,
	output					o_ackL,
	input					i_reqL,
	input					i_ackR
);	

	// Light_A & Light_B
	parameter		S_S0	= 2'b00;	
	parameter		S_S1	= 2'b01;
	parameter		S_S2	= 2'b10;
	parameter		S_S3	= 2'b11;

	parameter		M_S0	= 1'b0;
	parameter		M_S1	= 1'b1;

	parameter		L_R		= 2'b00;
	parameter		L_G		= 2'b01;
	parameter		L_Y		= 2'b10;

	wire			click,reqR,reqL,ackL,ackR;
	click
	u_click(
		.o_click	(click		),
		.o_reqR		(o_reqR		),
		.o_ackL		(o_ackL		),
		.i_reqL		(i_reqL		),
		.i_ackR		(i_ackR		),
		.i_rstn		(i_rstn		)
	);
	//	For Mode FSM Output
	reg						mode;

	//	Main State Register
	reg				[1:0]	nState;
	reg				[1:0]	cState;
	always @(posedge click or negedge i_rstn) begin
		if(!i_rstn) begin
			cState	<= S_S0;
		end else begin
			cState	<= nState;
		end
	end

	// Sub State Register
	reg						nMode;
	reg						cMode;
	always @(posedge click or negedge i_rstn) begin
		if(!i_rstn) begin
			cMode	<= M_S0;
		end else begin
			cMode	<= nMode;
		end
	end

	// Next State Logic
	always @(*) begin
		case (cState)
			S_S0:	nState	= i_traffic_a ? S_S0 : S_S1;
			S_S1:	nState	= S_S2;
			S_S2:	nState	= (mode | i_traffic_b) ? S_S2 : S_S3;
			S_S3:	nState	= S_S0;
		endcase
	end

	// Next Mode Logic
	always @(*) begin
		case (cMode)
			M_S0:	nMode	= i_mode_p ? M_S1 : M_S0;
			M_S1:	nMode	= i_mode_r ? M_S0 : M_S1;
		endcase
	end

	reg		[1:0]	light_a, light_b;
	// Output Logic(Light)
	always @(*) begin
		case (cState)
			S_S0:	{light_a, light_b} = {L_G, L_R};
			S_S1:	{light_a, light_b} = {L_Y, L_R};
			S_S2:	{light_a, light_b} = {L_R, L_G};
			S_S3:	{light_a, light_b} = {L_R, L_Y};
		endcase
	end
	assign	#(5) o_light_a = light_a;
	assign	#(5) o_light_b = light_b;

	// Output Logic(Mode)
	always @(*) begin
		case (cMode)
			M_S0:	mode = 1'b0;
			M_S1:	mode = 1'b1;
		endcase
	end

	`ifdef DEBUG
		reg			[8*8-1:0]	strLA;
		reg			[8*8-1:0]	strLB;
		always @(*) begin
			case (o_light_a)
				L_G: strLA		= "GREEN";
				L_R: strLA		= "RED";
				L_Y: strLA		= "YELLOW";
			endcase
			case (o_light_b)
				L_G: strLB		= "GREEN";
				L_R: strLB		= "RED";
				L_Y: strLB		= "YELLOW";
			endcase
		end
	`endif

	endmodule

practice/fsm_tb.v
// ===================================================
//	=================[ VLSISYS Lab. ]=================
//	* Author		: oksj (oksj@sookmyung.ac.kr)
//	* Filename		: fsm_tb.v
//	* Date			: 2025-03-05 
//	* Description	: 
// ===================================================
// --------------------------------------------------
//	Define Global Variables
// --------------------------------------------------
`define	CLKFREQ		100		// Clock Freq. (Unit: MHz)
`define	SIMCYCLE	`NVEC	// Sim. Cycles
`define NVEC		100		// # of Test Vector
`define	DEBUG		

// --------------------------------------------------
//	Includes
// --------------------------------------------------
`include	"fsm.v"

module fsm_tb;
// --------------------------------------------------
//	DUT Signals & Instantiate
// --------------------------------------------------
	wire			[1:0]	o_light_a;
	wire			[1:0]	o_light_b;
	reg						i_traffic_a;
	reg						i_traffic_b;
	reg						i_mode_p;
	reg						i_mode_r;
	reg						i_rstn;
	wire					o_reqR;
	wire					o_ackL;
	reg						i_reqL;
	reg						i_ackR;

	fsm
	u_fsm(
		.o_light_a			(o_light_a			),
		.o_light_b			(o_light_b			),
		.i_traffic_a		(i_traffic_a		),
		.i_traffic_b		(i_traffic_b		),
		.i_mode_p			(i_mode_p			),
		.i_mode_r			(i_mode_r			),
		.i_rstn				(i_rstn				),
		.o_reqR				(o_reqR				),
		.o_ackL				(o_ackL				),
		.i_reqL				(i_reqL				),
		.i_ackR				(i_ackR				)
	);


// --------------------------------------------------
//	Tasks	
// --------------------------------------------------
	reg		[8*32-1:0]		taskState;
	task init;
		begin
			taskState	= "Init(Reset)";
			i_traffic_a	= 1'b0;
			i_traffic_b	= 1'b0;
			i_mode_p	= 1'b0;
			i_mode_r	= 1'b0;
			i_rstn		= 1'b0;
			i_reqL		= 1'b0;
			i_ackR		= 1'b0;
		end
	endtask

	task reset_n_cycle;
		input	[3:0]	n;
		begin
			#(n*1000/`CLKFREQ);
			taskState	= "Operate";
			i_rstn		= 1'b1;
		end
	endtask


// --------------------------------------------------
//	Test Stimulus
// --------------------------------------------------
	integer		i, j;
	initial begin
		init();
		reset_n_cycle(4);

		i_reqL=1;
		{i_traffic_a, i_traffic_b} = $urandom;
		{i_mode_p, i_mode_r} = 2'b00;
		#30;
		i_reqL=0;i_ackR=1;
		#30;

		i_reqL=1;i_ackR=0;
		{i_traffic_a, i_traffic_b} = $urandom;
		{i_mode_p, i_mode_r} = 2'b00;
		#30;
		i_reqL=0;i_ackR=1;
		#30;

		i_reqL=1;i_ackR=0;
		{i_traffic_a, i_traffic_b} = $urandom;
		{i_mode_p, i_mode_r} = 2'b10;
		#30;
		i_reqL=0;i_ackR=1;
		#30;

		i_reqL=1;i_ackR=0;
		{i_traffic_a, i_traffic_b} = $urandom;
		{i_mode_p, i_mode_r} = 2'b10;
		#30;
		i_reqL=0;i_ackR=1;
		#30;
		
		i_reqL=1;i_ackR=0;
		{i_traffic_a, i_traffic_b} = $urandom;
		{i_mode_p, i_mode_r} = 2'b01;
		#30;
		i_reqL=0;i_ackR=1;
		#30;

		i_reqL=1;i_ackR=0;
		{i_traffic_a, i_traffic_b} = $urandom;
		{i_mode_p, i_mode_r} = 2'b01;
		#30;
		i_reqL=0;i_ackR=1;
		#30;

		#(1000/`CLKFREQ);
		$finish;
	end

// --------------------------------------------------
//	Dump VCD
// --------------------------------------------------
	reg	[8*32-1:0]	vcd_file;
	initial begin
		if ($value$plusargs("vcd_file=%s", vcd_file)) begin
			$dumpfile(vcd_file);
			$dumpvars;
		end else begin
			$dumpfile("fsm_tb.vcd");
			$dumpvars;
		end
	end

endmodule

practice/vcd/fsm.vcd
$date
	Wed Mar  5 22:57:23 2025
$end
$version
	Icarus Verilog
$end
$timescale
	1ps
$end
$scope module fsm_tb $end
$var wire 1 ! o_reqR $end
$var wire 2 " o_light_b [1:0] $end
$var wire 2 # o_light_a [1:0] $end
$var wire 1 $ o_ackL $end
$var reg 1 % i_ackR $end
$var reg 1 & i_mode_p $end
$var reg 1 ' i_mode_r $end
$var reg 1 ( i_reqL $end
$var reg 1 ) i_rstn $end
$var reg 1 * i_traffic_a $end
$var reg 1 + i_traffic_b $end
$var reg 256 , taskState [255:0] $end
$var reg 256 - vcd_file [255:0] $end
$scope module u_fsm $end
$var wire 1 % i_ackR $end
$var wire 1 & i_mode_p $end
$var wire 1 ' i_mode_r $end
$var wire 1 ( i_reqL $end
$var wire 1 ) i_rstn $end
$var wire 1 * i_traffic_a $end
$var wire 1 + i_traffic_b $end
$var wire 2 . o_light_a [1:0] $end
$var wire 2 / o_light_b [1:0] $end
$var wire 1 ! o_reqR $end
$var wire 1 $ o_ackL $end
$var wire 1 0 click $end
$var reg 1 1 cMode $end
$var reg 2 2 cState [1:0] $end
$var reg 2 3 light_a [1:0] $end
$var reg 2 4 light_b [1:0] $end
$var reg 1 5 mode $end
$var reg 1 6 nMode $end
$var reg 2 7 nState [1:0] $end
$var reg 64 8 strLA [63:0] $end
$var reg 64 9 strLB [63:0] $end
$scope module u_click $end
$var wire 1 : and_out $end
$var wire 1 % i_ackR $end
$var wire 1 ( i_reqL $end
$var wire 1 ) i_rstn $end
$var wire 1 ; n_dff_outL $end
$var wire 1 < n_dff_outR $end
$var wire 1 $ o_ackL $end
$var wire 1 0 o_click $end
$var wire 1 ! o_reqR $end
$var wire 1 = xnor_out $end
$var wire 1 > xor_out $end
$var wire 1 ? dff_outR $end
$var wire 1 @ dff_outL $end
$scope module u_dffL $end
$var wire 1 : i_clk $end
$var wire 1 ; i_d $end
$var wire 1 ) i_rstn $end
$var wire 1 @ o_q $end
$var reg 1 A q_internal $end
$upscope $end
$scope module u_dffR $end
$var wire 1 : i_clk $end
$var wire 1 < i_d $end
$var wire 1 ) i_rstn $end
$var wire 1 ? o_q $end
$var reg 1 B q_internal $end
$upscope $end
$upscope $end
$upscope $end
$scope task init $end
$upscope $end
$scope task reset_n_cycle $end
$var reg 4 C n [3:0] $end
$upscope $end
$upscope $end
$enddefinitions $end
#0
$dumpvars
b100 C
0B
0A
x@
x?
x>
x=
x<
x;
x:
bx 9
bx 8
b1 7
06
05
b0 4
b1 3
b0 2
01
x0
bx /
bx .
b101110001011110111011001100011011001000010111101100110011100110110110100101110011101100110001101100100 -
b100100101101110011010010111010000101000010100100110010101110011011001010111010000101001 ,
0+
0*
0)
0(
0'
0&
0%
x$
bx #
bx "
x!
$end
#3000
0$
0@
0!
0?
#5000
b10100100100010101000100 9
b100011101010010010001010100010101001110 8
b1 #
b1 .
b0 "
b0 /
#6000
1;
1<
#9000
0>
#12000
1=
#13000
00
0:
#40000
1(
1)
b1001111011100000110010101110010011000010111010001100101 ,
#46000
1>
#50000
b10 3
b10 7
b1 2
1B
1A
10
1:
#53000
1!
1?
1$
1@
#55000
b10110010100010101001100010011000100111101010111 8
b10 #
b10 .
#56000
0<
0;
#59000
0>
#62000
0=
#63000
00
0:
#70000
1%
0(
#76000
1>
#79000
1=
#83000
b0 3
b1 4
b11 7
b10 2
0A
0B
10
1:
#86000
0$
0@
0!
0?
#88000
b100011101010010010001010100010101001110 9
b10100100100010101000100 8
b0 #
b0 .
b1 "
b1 /
#89000
1;
1<
#92000
0>
#95000
0=
#96000
00
0:
#100000
b10 7
1+
0%
1(
#106000
1>
#109000
1=
#113000
1B
1A
10
1:
#116000
1!
1?
1$
1@
#119000
0<
0;
#122000
0>
#125000
0=
#126000
00
0:
#130000
1%
0(
#136000
1>
#139000
1=
#143000
0A
0B
10
1:
#146000
0$
0@
0!
0?
#149000
1;
1<
#152000
0>
#155000
0=
#156000
00
0:
#160000
16
1&
0%
1(
#166000
1>
#169000
1=
#173000
15
11
1B
1A
10
1:
#176000
1!
1?
1$
1@
#179000
0<
0;
#182000
0>
#185000
0=
#186000
00
0:
#190000
1%
0(
#196000
1>
#199000
1=
#203000
0A
0B
10
1:
#206000
0$
0@
0!
0?
#209000
1;
1<
#212000
0>
#215000
0=
#216000
00
0:
#220000
1*
0%
1(
#226000
1>
#229000
1=
#233000
1B
1A
10
1:
#236000
1!
1?
1$
1@
#239000
0<
0;
#242000
0>
#245000
0=
#246000
00
0:
#250000
1%
0(
#256000
1>
#259000
1=
#263000
0A
0B
10
1:
#266000
0$
0@
0!
0?
#269000
1;
1<
#272000
0>
#275000
0=
#276000
00
0:
#280000
06
0&
1'
0*
0%
1(
#286000
1>
#289000
1=
#293000
05
01
1B
1A
10
1:
#296000
1!
1?
1$
1@
#299000
0<
0;
#302000
0>
#305000
0=
#306000
00
0:
#310000
1%
0(
#316000
1>
#319000
1=
#323000
0A
0B
10
1:
#326000
0$
0@
0!
0?
#329000
1;
1<
#332000
0>
#335000
0=
#336000
00
0:
#340000
0%
1(
#346000
1>
#349000
1=
#353000
1B
1A
10
1:
#356000
1!
1?
1$
1@
#359000
0<
0;
#362000
0>
#365000
0=
#366000
00
0:
#370000
1%
0(
#376000
1>
#379000
1=
#383000
0A
0B
10
1:
#386000
0$
0@
0!
0?
#389000
1;
1<
#392000
0>
#395000
0=
#396000
00
0:
