practice/gray_code_converter.v
// ===================================================
//	=================[ VLSISYS Lab. ]=================
//	* Author		: oksj (oksj@sookmyung.ac.kr)
//	* Filename		: gray_code_converter.v
//	* Description	: 
// ===================================================
module bin_to_gray
(
	output		[7:0]	out_gray,
	input		[7:0]	in_bin
);

	//MSB is alsways same
	assign		out_gray[7]	= in_bin[7];	
	
	// xor delay is 6ns
	xor	#(6)	(out_gray[0], in_bin[1], in_bin[0]);	
	xor	#(6)	(out_gray[1], in_bin[2], in_bin[1]);	
	xor	#(6)	(out_gray[2], in_bin[3], in_bin[2]);	
	xor	#(6)	(out_gray[3], in_bin[4], in_bin[3]);	
	xor	#(6)	(out_gray[4], in_bin[5], in_bin[4]);	
	xor	#(6)	(out_gray[5], in_bin[6], in_bin[5]);	
	xor	#(6)	(out_gray[6], in_bin[7], in_bin[6]);	
endmodule

module gray_to_bin 
(
	output		[7:0]	out_bin,
	input		[7:0]	in_gray
);
	
	// MSB is always same
	assign		out_bin[7]	= in_gray[7];

	// xor delay is 6ns
	xor	#(6)	(out_bin[6], out_bin[7], in_gray[6]); 	
	xor	#(6)	(out_bin[5], out_bin[6], in_gray[5]); 	
	xor	#(6)	(out_bin[4], out_bin[5], in_gray[4]); 	
	xor	#(6)	(out_bin[3], out_bin[4], in_gray[3]); 	
	xor	#(6)	(out_bin[2], out_bin[3], in_gray[2]); 	
	xor	#(6)	(out_bin[1], out_bin[2], in_gray[1]); 	
	xor	#(6)	(out_bin[0], out_bin[1], in_gray[0]); 	
endmodule

practice/gray_code_converter_tb.v
// ===================================================
//	=================[ VLSISYS Lab. ]=================
//	* Author		: oksj (oksj@sookmyung.ac.kr)
//	* Filename		: gray_code_converter_tb.v
//	* Date			: 2025-03-06 
//	* Description	: 
// ===================================================
// --------------------------------------------------
//	Define Global Variables
// --------------------------------------------------
`define	CLKFREQ		100		// Clock Freq. (Unit: MHz)
`define	SIMCYCLE	`NVEC	// Sim. Cycles
`define NVEC		100		// # of Test Vector

// --------------------------------------------------
//	Includes
// --------------------------------------------------
`include	"gray_code_converter.v"

module gray_code_converter_tb;
// --------------------------------------------------
//	DUT Signals & Instantiate
// --------------------------------------------------
	wire	[7:0]	out_gray;
	wire	[7:0]	out_bin;
	reg		[7:0]	i_data;

	bin_to_gray
	u_bin_to_gray(
		.out_gray	(out_gray		),
		.in_bin		(i_data			)
	);

	gray_to_bin
	u_gray_to_bin(
		.out_bin	(out_bin		),
		.in_gray	(out_gray		)
	);

	task	init;
		begin	
			i_data =0;
		end
	endtask



// --------------------------------------------------
//	Test Stimulus
// --------------------------------------------------
	integer		i, j;
	initial begin
		init();

		for (i=0; i<`SIMCYCLE; i++) begin
			i_data = i;
			#(30);
		end
		$finish;
	end

// --------------------------------------------------
//	Dump VCD
// --------------------------------------------------
	reg	[8*32-1:0]	vcd_file;
	initial begin
		if ($value$plusargs("vcd_file=%s", vcd_file)) begin
			$dumpfile(vcd_file);
			$dumpvars;
		end else begin
			$dumpfile("gray_code_converter_tb.vcd");
			$dumpvars;
		end
	end

endmodule

practice/vcd/gray_code_converter.vcd
$date
	Thu Mar  6 09:43:20 2025
$end
$version
	Icarus Verilog
$end
$timescale
	1ps
$end
$scope module gray_code_converter_tb $end
$var wire 8 ! out_gray [7:0] $end
$var wire 8 " out_bin [7:0] $end
$var reg 8 # i_data [7:0] $end
$var reg 256 $ vcd_file [255:0] $end
$var integer 32 % i [31:0] $end
$scope module u_bin_to_gray $end
$var wire 8 & in_bin [7:0] $end
$var wire 8 ' out_gray [7:0] $end
$upscope $end
$scope module u_gray_to_bin $end
$var wire 8 ( in_gray [7:0] $end
$var wire 8 ) out_bin [7:0] $end
$upscope $end
$scope task init $end
$upscope $end
$upscope $end
$enddefinitions $end
#0
$dumpvars
b0xxxxxxx )
b0xxxxxxx (
b0xxxxxxx '
b0 &
b0 %
b10111000101111011101100110001101100100001011110110011101110010011000010111100101011111011000110110111101100100011001010101111101100011011011110110111001110110011001010111001001110100011001010111001000101110011101100110001101100100 $
b0 #
b0xxxxxxx "
b0xxxxxxx !
$end
#6000
b0 !
b0 '
b0 (
#12000
b0xxxxxx "
b0xxxxxx )
#18000
b0xxxxx "
b0xxxxx )
#24000
b0xxxx "
b0xxxx )
#30000
b0xxx "
b0xxx )
b1 #
b1 &
b1 %
#36000
b0xx "
b0xx )
b1 !
b1 '
b1 (
#42000
b0x "
b0x )
#48000
b1 "
b1 )
#60000
b10 #
b10 &
b10 %
#66000
b11 !
b11 '
b11 (
#72000
b11 "
b11 )
#78000
b10 "
b10 )
#90000
b11 #
b11 &
b11 %
#96000
b10 !
b10 '
b10 (
#102000
b11 "
b11 )
#120000
b100 #
b100 &
b100 %
#126000
b110 !
b110 '
b110 (
#132000
b111 "
b111 )
#138000
b101 "
b101 )
#144000
b100 "
b100 )
#150000
b101 #
b101 &
b101 %
#156000
b111 !
b111 '
b111 (
#162000
b101 "
b101 )
#180000
b110 #
b110 &
b110 %
#186000
b101 !
b101 '
b101 (
#192000
b111 "
b111 )
#198000
b110 "
b110 )
#210000
b111 #
b111 &
b111 %
#216000
b100 !
b100 '
b100 (
#222000
b111 "
b111 )
#240000
b1000 #
b1000 &
b1000 %
#246000
b1100 !
b1100 '
b1100 (
#252000
b1111 "
b1111 )
#258000
b1011 "
b1011 )
#264000
b1001 "
b1001 )
#270000
b1000 "
b1000 )
b1001 #
b1001 &
b1001 %
#276000
b1101 !
b1101 '
b1101 (
#282000
b1001 "
b1001 )
#300000
b1010 #
b1010 &
b1010 %
#306000
b1111 !
b1111 '
b1111 (
#312000
b1011 "
b1011 )
#318000
b1010 "
b1010 )
#330000
b1011 #
b1011 &
b1011 %
#336000
b1110 !
b1110 '
b1110 (
#342000
b1011 "
b1011 )
#360000
b1100 #
b1100 &
b1100 %
#366000
b1010 !
b1010 '
b1010 (
#372000
b1111 "
b1111 )
#378000
b1101 "
b1101 )
#384000
b1100 "
b1100 )
#390000
b1101 #
b1101 &
b1101 %
#396000
b1011 !
b1011 '
b1011 (
#402000
b1101 "
b1101 )
#420000
b1110 #
b1110 &
b1110 %
#426000
b1001 !
b1001 '
b1001 (
#432000
b1111 "
b1111 )
#438000
b1110 "
b1110 )
#450000
b1111 #
b1111 &
b1111 %
#456000
b1000 !
b1000 '
b1000 (
#462000
b1111 "
b1111 )
#480000
b10000 #
b10000 &
b10000 %
#486000
b11000 !
b11000 '
b11000 (
#492000
b11111 "
b11111 )
#498000
b10111 "
b10111 )
#504000
b10011 "
b10011 )
#510000
b10001 "
b10001 )
b10001 #
b10001 &
b10001 %
#516000
b10000 "
b10000 )
b11001 !
b11001 '
b11001 (
#522000
b10001 "
b10001 )
#540000
b10010 #
b10010 &
b10010 %
#546000
b11011 !
b11011 '
b11011 (
#552000
b10011 "
b10011 )
#558000
b10010 "
b10010 )
#570000
b10011 #
b10011 &
b10011 %
#576000
b11010 !
b11010 '
b11010 (
#582000
b10011 "
b10011 )
#600000
b10100 #
b10100 &
b10100 %
#606000
b11110 !
b11110 '
b11110 (
#612000
b10111 "
b10111 )
#618000
b10101 "
b10101 )
#624000
b10100 "
b10100 )
#630000
b10101 #
b10101 &
b10101 %
#636000
b11111 !
b11111 '
b11111 (
#642000
b10101 "
b10101 )
#660000
b10110 #
b10110 &
b10110 %
#666000
b11101 !
b11101 '
b11101 (
#672000
b10111 "
b10111 )
#678000
b10110 "
b10110 )
#690000
b10111 #
b10111 &
b10111 %
#696000
b11100 !
b11100 '
b11100 (
#702000
b10111 "
b10111 )
#720000
b11000 #
b11000 &
b11000 %
#726000
b10100 !
b10100 '
b10100 (
#732000
b11111 "
b11111 )
#738000
b11011 "
b11011 )
#744000
b11001 "
b11001 )
#750000
b11000 "
b11000 )
b11001 #
b11001 &
b11001 %
#756000
b10101 !
b10101 '
b10101 (
#762000
b11001 "
b11001 )
#780000
b11010 #
b11010 &
b11010 %
#786000
b10111 !
b10111 '
b10111 (
#792000
b11011 "
b11011 )
#798000
b11010 "
b11010 )
#810000
b11011 #
b11011 &
b11011 %
#816000
b10110 !
b10110 '
b10110 (
#822000
b11011 "
b11011 )
#840000
b11100 #
b11100 &
b11100 %
#846000
b10010 !
b10010 '
b10010 (
#852000
b11111 "
b11111 )
#858000
b11101 "
b11101 )
#864000
b11100 "
b11100 )
#870000
b11101 #
b11101 &
b11101 %
#876000
b10011 !
b10011 '
b10011 (
#882000
b11101 "
b11101 )
#900000
b11110 #
b11110 &
b11110 %
#906000
b10001 !
b10001 '
b10001 (
#912000
b11111 "
b11111 )
#918000
b11110 "
b11110 )
#930000
b11111 #
b11111 &
b11111 %
#936000
b10000 !
b10000 '
b10000 (
#942000
b11111 "
b11111 )
#960000
b100000 #
b100000 &
b100000 %
#966000
b110000 !
b110000 '
b110000 (
#972000
b111111 "
b111111 )
#978000
b101111 "
b101111 )
#984000
b100111 "
b100111 )
#990000
b100011 "
b100011 )
b100001 #
b100001 &
b100001 %
#996000
b100001 "
b100001 )
b110001 !
b110001 '
b110001 (
#1020000
b100010 #
b100010 &
b100010 %
#1026000
b110011 !
b110011 '
b110011 (
#1032000
b100011 "
b100011 )
#1038000
b100010 "
b100010 )
#1050000
b100011 #
b100011 &
b100011 %
#1056000
b110010 !
b110010 '
b110010 (
#1062000
b100011 "
b100011 )
#1080000
b100100 #
b100100 &
b100100 %
#1086000
b110110 !
b110110 '
b110110 (
#1092000
b100111 "
b100111 )
#1098000
b100101 "
b100101 )
#1104000
b100100 "
b100100 )
#1110000
b100101 #
b100101 &
b100101 %
#1116000
b110111 !
b110111 '
b110111 (
#1122000
b100101 "
b100101 )
#1140000
b100110 #
b100110 &
b100110 %
#1146000
b110101 !
b110101 '
b110101 (
#1152000
b100111 "
b100111 )
#1158000
b100110 "
b100110 )
#1170000
b100111 #
b100111 &
b100111 %
#1176000
b110100 !
b110100 '
b110100 (
#1182000
b100111 "
b100111 )
#1200000
b101000 #
b101000 &
b101000 %
#1206000
b111100 !
b111100 '
b111100 (
#1212000
b101111 "
b101111 )
#1218000
b101011 "
b101011 )
#1224000
b101001 "
b101001 )
#1230000
b101000 "
b101000 )
b101001 #
b101001 &
b101001 %
#1236000
b111101 !
b111101 '
b111101 (
#1242000
b101001 "
b101001 )
#1260000
b101010 #
b101010 &
b101010 %
#1266000
b111111 !
b111111 '
b111111 (
#1272000
b101011 "
b101011 )
#1278000
b101010 "
b101010 )
#1290000
b101011 #
b101011 &
b101011 %
#1296000
b111110 !
b111110 '
b111110 (
#1302000
b101011 "
b101011 )
#1320000
b101100 #
b101100 &
b101100 %
#1326000
b111010 !
b111010 '
b111010 (
#1332000
b101111 "
b101111 )
#1338000
b101101 "
b101101 )
#1344000
b101100 "
b101100 )
#1350000
b101101 #
b101101 &
b101101 %
#1356000
b111011 !
b111011 '
b111011 (
#1362000
b101101 "
b101101 )
#1380000
b101110 #
b101110 &
b101110 %
#1386000
b111001 !
b111001 '
b111001 (
#1392000
b101111 "
b101111 )
#1398000
b101110 "
b101110 )
#1410000
b101111 #
b101111 &
b101111 %
#1416000
b111000 !
b111000 '
b111000 (
#1422000
b101111 "
b101111 )
#1440000
b110000 #
b110000 &
b110000 %
#1446000
b101000 !
b101000 '
b101000 (
#1452000
b111111 "
b111111 )
#1458000
b110111 "
b110111 )
#1464000
b110011 "
b110011 )
#1470000
b110001 "
b110001 )
b110001 #
b110001 &
b110001 %
#1476000
b110000 "
b110000 )
b101001 !
b101001 '
b101001 (
#1482000
b110001 "
b110001 )
#1500000
b110010 #
b110010 &
b110010 %
#1506000
b101011 !
b101011 '
b101011 (
#1512000
b110011 "
b110011 )
#1518000
b110010 "
b110010 )
#1530000
b110011 #
b110011 &
b110011 %
#1536000
b101010 !
b101010 '
b101010 (
#1542000
b110011 "
b110011 )
#1560000
b110100 #
b110100 &
b110100 %
#1566000
b101110 !
b101110 '
b101110 (
#1572000
b110111 "
b110111 )
#1578000
b110101 "
b110101 )
#1584000
b110100 "
b110100 )
#1590000
b110101 #
b110101 &
b110101 %
#1596000
b101111 !
b101111 '
b101111 (
#1602000
b110101 "
b110101 )
#1620000
b110110 #
b110110 &
b110110 %
#1626000
b101101 !
b101101 '
b101101 (
#1632000
b110111 "
b110111 )
#1638000
b110110 "
b110110 )
#1650000
b110111 #
b110111 &
b110111 %
#1656000
b101100 !
b101100 '
b101100 (
#1662000
b110111 "
b110111 )
#1680000
b111000 #
b111000 &
b111000 %
#1686000
b100100 !
b100100 '
b100100 (
#1692000
b111111 "
b111111 )
#1698000
b111011 "
b111011 )
#1704000
b111001 "
b111001 )
#1710000
b111000 "
b111000 )
b111001 #
b111001 &
b111001 %
#1716000
b100101 !
b100101 '
b100101 (
#1722000
b111001 "
b111001 )
#1740000
b111010 #
b111010 &
b111010 %
#1746000
b100111 !
b100111 '
b100111 (
#1752000
b111011 "
b111011 )
#1758000
b111010 "
b111010 )
#1770000
b111011 #
b111011 &
b111011 %
#1776000
b100110 !
b100110 '
b100110 (
#1782000
b111011 "
b111011 )
#1800000
b111100 #
b111100 &
b111100 %
#1806000
b100010 !
b100010 '
b100010 (
#1812000
b111111 "
b111111 )
#1818000
b111101 "
b111101 )
#1824000
b111100 "
b111100 )
#1830000
b111101 #
b111101 &
b111101 %
#1836000
b100011 !
b100011 '
b100011 (
#1842000
b111101 "
b111101 )
#1860000
b111110 #
b111110 &
b111110 %
#1866000
b100001 !
b100001 '
b100001 (
#1872000
b111111 "
b111111 )
#1878000
b111110 "
b111110 )
#1890000
b111111 #
b111111 &
b111111 %
#1896000
b100000 !
b100000 '
b100000 (
#1902000
b111111 "
b111111 )
#1920000
b1000000 #
b1000000 &
b1000000 %
#1926000
b1100000 !
b1100000 '
b1100000 (
#1932000
b1111111 "
b1111111 )
#1938000
b1011111 "
b1011111 )
#1944000
b1001111 "
b1001111 )
#1950000
b1000111 "
b1000111 )
b1000001 #
b1000001 &
b1000001 %
#1956000
b1000011 "
b1000011 )
b1100001 !
b1100001 '
b1100001 (
#1962000
b1000000 "
b1000000 )
#1968000
b1000001 "
b1000001 )
#1980000
b1000010 #
b1000010 &
b1000010 %
#1986000
b1100011 !
b1100011 '
b1100011 (
#1992000
b1000011 "
b1000011 )
#1998000
b1000010 "
b1000010 )
#2010000
b1000011 #
b1000011 &
b1000011 %
#2016000
b1100010 !
b1100010 '
b1100010 (
#2022000
b1000011 "
b1000011 )
#2040000
b1000100 #
b1000100 &
b1000100 %
#2046000
b1100110 !
b1100110 '
b1100110 (
#2052000
b1000111 "
b1000111 )
#2058000
b1000101 "
b1000101 )
#2064000
b1000100 "
b1000100 )
#2070000
b1000101 #
b1000101 &
b1000101 %
#2076000
b1100111 !
b1100111 '
b1100111 (
#2082000
b1000101 "
b1000101 )
#2100000
b1000110 #
b1000110 &
b1000110 %
#2106000
b1100101 !
b1100101 '
b1100101 (
#2112000
b1000111 "
b1000111 )
#2118000
b1000110 "
b1000110 )
#2130000
b1000111 #
b1000111 &
b1000111 %
#2136000
b1100100 !
b1100100 '
b1100100 (
#2142000
b1000111 "
b1000111 )
#2160000
b1001000 #
b1001000 &
b1001000 %
#2166000
b1101100 !
b1101100 '
b1101100 (
#2172000
b1001111 "
b1001111 )
#2178000
b1001011 "
b1001011 )
#2184000
b1001001 "
b1001001 )
#2190000
b1001000 "
b1001000 )
b1001001 #
b1001001 &
b1001001 %
#2196000
b1101101 !
b1101101 '
b1101101 (
#2202000
b1001001 "
b1001001 )
#2220000
b1001010 #
b1001010 &
b1001010 %
#2226000
b1101111 !
b1101111 '
b1101111 (
#2232000
b1001011 "
b1001011 )
#2238000
b1001010 "
b1001010 )
#2250000
b1001011 #
b1001011 &
b1001011 %
#2256000
b1101110 !
b1101110 '
b1101110 (
#2262000
b1001011 "
b1001011 )
#2280000
b1001100 #
b1001100 &
b1001100 %
#2286000
b1101010 !
b1101010 '
b1101010 (
#2292000
b1001111 "
b1001111 )
#2298000
b1001101 "
b1001101 )
#2304000
b1001100 "
b1001100 )
#2310000
b1001101 #
b1001101 &
b1001101 %
#2316000
b1101011 !
b1101011 '
b1101011 (
#2322000
b1001101 "
b1001101 )
#2340000
b1001110 #
b1001110 &
b1001110 %
#2346000
b1101001 !
b1101001 '
b1101001 (
#2352000
b1001111 "
b1001111 )
#2358000
b1001110 "
b1001110 )
#2370000
b1001111 #
b1001111 &
b1001111 %
#2376000
b1101000 !
b1101000 '
b1101000 (
#2382000
b1001111 "
b1001111 )
#2400000
b1010000 #
b1010000 &
b1010000 %
#2406000
b1111000 !
b1111000 '
b1111000 (
#2412000
b1011111 "
b1011111 )
#2418000
b1010111 "
b1010111 )
#2424000
b1010011 "
b1010011 )
#2430000
b1010001 "
b1010001 )
b1010001 #
b1010001 &
b1010001 %
#2436000
b1010000 "
b1010000 )
b1111001 !
b1111001 '
b1111001 (
#2442000
b1010001 "
b1010001 )
#2460000
b1010010 #
b1010010 &
b1010010 %
#2466000
b1111011 !
b1111011 '
b1111011 (
#2472000
b1010011 "
b1010011 )
#2478000
b1010010 "
b1010010 )
#2490000
b1010011 #
b1010011 &
b1010011 %
#2496000
b1111010 !
b1111010 '
b1111010 (
#2502000
b1010011 "
b1010011 )
#2520000
b1010100 #
b1010100 &
b1010100 %
#2526000
b1111110 !
b1111110 '
b1111110 (
#2532000
b1010111 "
b1010111 )
#2538000
b1010101 "
b1010101 )
#2544000
b1010100 "
b1010100 )
#2550000
b1010101 #
b1010101 &
b1010101 %
#2556000
b1111111 !
b1111111 '
b1111111 (
#2562000
b1010101 "
b1010101 )
#2580000
b1010110 #
b1010110 &
b1010110 %
#2586000
b1111101 !
b1111101 '
b1111101 (
#2592000
b1010111 "
b1010111 )
#2598000
b1010110 "
b1010110 )
#2610000
b1010111 #
b1010111 &
b1010111 %
#2616000
b1111100 !
b1111100 '
b1111100 (
#2622000
b1010111 "
b1010111 )
#2640000
b1011000 #
b1011000 &
b1011000 %
#2646000
b1110100 !
b1110100 '
b1110100 (
#2652000
b1011111 "
b1011111 )
#2658000
b1011011 "
b1011011 )
#2664000
b1011001 "
b1011001 )
#2670000
b1011000 "
b1011000 )
b1011001 #
b1011001 &
b1011001 %
#2676000
b1110101 !
b1110101 '
b1110101 (
#2682000
b1011001 "
b1011001 )
#2700000
b1011010 #
b1011010 &
b1011010 %
#2706000
b1110111 !
b1110111 '
b1110111 (
#2712000
b1011011 "
b1011011 )
#2718000
b1011010 "
b1011010 )
#2730000
b1011011 #
b1011011 &
b1011011 %
#2736000
b1110110 !
b1110110 '
b1110110 (
#2742000
b1011011 "
b1011011 )
#2760000
b1011100 #
b1011100 &
b1011100 %
#2766000
b1110010 !
b1110010 '
b1110010 (
#2772000
b1011111 "
b1011111 )
#2778000
b1011101 "
b1011101 )
#2784000
b1011100 "
b1011100 )
#2790000
b1011101 #
b1011101 &
b1011101 %
#2796000
b1110011 !
b1110011 '
b1110011 (
#2802000
b1011101 "
b1011101 )
#2820000
b1011110 #
b1011110 &
b1011110 %
#2826000
b1110001 !
b1110001 '
b1110001 (
#2832000
b1011111 "
b1011111 )
#2838000
b1011110 "
b1011110 )
#2850000
b1011111 #
b1011111 &
b1011111 %
#2856000
b1110000 !
b1110000 '
b1110000 (
#2862000
b1011111 "
b1011111 )
#2880000
b1100000 #
b1100000 &
b1100000 %
#2886000
b1010000 !
b1010000 '
b1010000 (
#2892000
b1111111 "
b1111111 )
#2898000
b1101111 "
b1101111 )
#2904000
b1100111 "
b1100111 )
#2910000
b1100011 "
b1100011 )
b1100001 #
b1100001 &
b1100001 %
#2916000
b1100001 "
b1100001 )
b1010001 !
b1010001 '
b1010001 (
#2940000
b1100010 #
b1100010 &
b1100010 %
#2946000
b1010011 !
b1010011 '
b1010011 (
#2952000
b1100011 "
b1100011 )
#2958000
b1100010 "
b1100010 )
#2970000
b1100011 #
b1100011 &
b1100011 %
#2976000
b1010010 !
b1010010 '
b1010010 (
#2982000
b1100011 "
b1100011 )
#3000000
b1100100 %
