practice/dff.v
// ===================================================
//	=================[ VLSISYS Lab. ]=================
//	* Author		: oksj (oksj@sookmyung.ac.kr)
//	* Filename		: dff.v
//	* Date			: 2025-03-05 
//	* Description	: 
// ===================================================


module dff
(
	output				o_q,
	input				i_d,
	input				i_clk,
	input				i_rstn
);

	reg	q_internal;

	always @(posedge i_clk or negedge i_rstn) begin
		if(!i_rstn) begin
			q_internal	<= 0;
		end else begin
			q_internal	<= i_d;
		end
	end

	buf	#(3) (o_q, q_internal);

	/*wire	r0, s0;
	wire	q0, q_0;

	nand	#(3)(s0, i_d, i_clk);
	nand	#(3)(r0, s0,i_clk);
	nand	#(3)(q0,q_0, s0);
	nand	#(3)(q_0, q0, r0);

	wire	n_clk;
	wire	r1, s1, q1, q_1;

	not		#(3)(n_clk, i_clk);
	nand	#(3)(s1, q0, n_clk);
	nand	#(3)(r1, s1, n_clk);
	nand	#(3)(q1, q_1,s1);
	nand	#(3)(q_1, q1, r1);

	assign	o_q = q1;
*/
endmodule

practice/click.v
// ===================================================
//	=================[ VLSISYS Lab. ]=================
//	* Author		: oksj (oksj@sookmyung.ac.kr)
//	* Filename		: click.v
//	* Date			: 2025-03-05 
//	* Description	: 
// ===================================================
`include		"dff.v"

module click 
(
	output		o_click,
	output		o_reqR,
	output		o_ackL,
	input 		i_reqL,
	input 		i_ackR,

	input 		i_rstn
);


	wire		xor_out, xnor_out, and_out;
	wire		dff_outL, dff_outR;

	xor		#(6)(xor_out, i_reqL, dff_outL);
	xnor	#(9)(xnor_out, dff_outR, i_ackR);
	and		#(4)(and_out, xor_out, xnor_out);

	wire		n_dff_outL, n_dff_outR;
	not		#(3)(n_dff_outL, dff_outL);
	not		#(3)(n_dff_outR, dff_outR);

	dff
	u_dffL(
		.o_q	(dff_outL	),
		.i_d	(n_dff_outL	),
		.i_clk	(and_out	),
		.i_rstn	(i_rstn		)
	);
	
	dff
	u_dffR(
		.o_q	(dff_outR	),
		.i_d	(n_dff_outR	),
		.i_clk	(and_out	),
		.i_rstn	(i_rstn		)
	);

	assign		o_click	= and_out;
	assign		o_reqR	= dff_outR;
	assign		o_ackL	= dff_outL;
	
endmodule

practice/click_three.v
// ===================================================
//	=================[ VLSISYS Lab. ]=================
//	* Author		: oksj (oksj@sookmyung.ac.kr)
//	* Filename		: click_three.v
//	* Description	: 
// ===================================================
`include			"click.v"

module click_three 
(
	output	o_click1,
	output	o_click2,
	output	o_click3,

	input	i_start,
	input	i_rstn
);
	
	wire	ack1, ack2, ack3;
	reg		req1;
	wire	req, req2, req3;
	wire	req_ack;

	click
	u_click1(
		.o_click	(o_click1	),
		.o_reqR		(req2		),
		.o_ackL		(ack1		),
		.i_reqL		(req1),
		.i_ackR		(ack2		),
		.i_rstn		(i_rstn		)
	);

	always @(*) begin
		if(ack1)
			req1 = ~req1;
		else
			req1 = i_start;
	end

	buf #(3) (req, ~req1);
	click
	u_click2(
		.o_click	(o_click2	),
		.o_reqR		(req3		),
		.o_ackL		(ack2		),
		.i_reqL		(req2		),
		.i_ackR		(ack3		),
		.i_rstn		(i_rstn		)
	);

	click
	u_click3(
		.o_click	(o_click3	),
		.o_reqR		(req_ack	),
		.o_ackL		(ack3		),
		.i_reqL		(req3		),
		.i_ackR		(req_ack),
		.i_rstn		(i_rstn		)
	);
endmodule

practice/stage3_piped.v
// ===================================================
//	=================[ VLSISYS Lab. ]=================
//	* Author		: oksj (oksj@sookmyung.ac.kr)
//	* Filename		: stage3_piped.v
//	* Description	: 
// ===================================================

`include		"click_three.v"

module stage3_piped 
(
	input	i_rstn,
	input	i_start,
	input	[7:0]	i_data,
	output	reg	[7:0]	o_data
);


	wire	click1, click2, click3;
	click_three
	u_click_three(
		.i_rstn		(i_rstn		),
		.i_start	(i_start	),
		.o_click1	(click1		),
		.o_click2	(click2		),
		.o_click3	(click3		)
	);

	reg	[7:0]	data1, data2, data3;
	always @(*) begin
		data1=  i_data;
	end
	always @(posedge click1 or negedge i_rstn) begin
		if(!i_rstn)
			data2	<= 0;
		else
			data2	<= data1;
	end
	
	always @(posedge click2 or negedge i_rstn) begin
		if(!i_rstn)
			data3	<= 0;
		else
			data3	<= data2;
	end

	always @(posedge click3 or negedge i_rstn) begin
		if(!i_rstn)
			o_data	<= 0;
		else
			o_data	<= data3;

	end
endmodule

practice/stage3_piped_tb.v
// ===================================================
//	=================[ VLSISYS Lab. ]=================
//	* Author		: oksj (oksj@sookmyung.ac.kr)
//	* Filename		: stage3_piped_tb.v
//	* Description	: 
// ===================================================
// --------------------------------------------------
//	Define Global Variables
// --------------------------------------------------
`define	CLKFREQ		100		// Clock Freq. (Unit: MHz)
`define	SIMCYCLE	`NVEC	// Sim. Cycles
`define NVEC		100		// # of Test Vector

// --------------------------------------------------
//	Includes
// --------------------------------------------------
`include	"stage3_piped.v"

module stage3_piped_tb;
// --------------------------------------------------
//	DUT Signals & Instantiate
// --------------------------------------------------

	reg		i_rstn;
	reg		i_start;
	reg		[7:0]	i_data;
	wire		[7:0]	o_data;

	stage3_piped
	u_stage3_piped(
		.i_rstn				(i_rstn			),
		.i_start			(i_start			),
		.i_data				(i_data				),
		.o_data				(o_data				)
	);




// --------------------------------------------------
//	Test Stimulus
// --------------------------------------------------
	integer		i, j;
	initial begin
		i_rstn=0;
		i_start=0;
		i_data=7'b1111_111;
		#(30);
		i_rstn=1;
		i_start=1;
		#(50);

		i_data=7'd0;
		#(10);
		i_data=7'd1;
		#(10);
		i_data=7'd2;
		#(10);
		i_data=7'd3;
		#(10);
		i_data=7'd4;
		#(10);
		i_data=7'd5;
		#(10);
		i_data=7'd6;
		#(10);
		i_data=7'd7;
		#(10);
		i_data=7'd8;

		#(300);

		#(1000/`CLKFREQ);
		$finish;
	end

// --------------------------------------------------
//	Dump VCD
// --------------------------------------------------
	reg	[8*32-1:0]	vcd_file;
	initial begin
		if ($value$plusargs("vcd_file=%s", vcd_file)) begin
			$dumpfile(vcd_file);
			$dumpvars;
		end else begin
			$dumpfile("stage3_piped_tb.vcd");
			$dumpvars;
		end
	end

endmodule

practice/vcd/stage3_piped.vcd
$date
	Fri Mar 14 06:10:00 2025
$end
$version
	Icarus Verilog
$end
$timescale
	1ps
$end
$scope module stage3_piped_tb $end
$var wire 8 ! o_data [7:0] $end
$var reg 8 " i_data [7:0] $end
$var reg 1 # i_rstn $end
$var reg 1 $ i_start $end
$var reg 256 % vcd_file [255:0] $end
$scope module u_stage3_piped $end
$var wire 8 & i_data [7:0] $end
$var wire 1 # i_rstn $end
$var wire 1 $ i_start $end
$var wire 1 ' click3 $end
$var wire 1 ( click2 $end
$var wire 1 ) click1 $end
$var reg 8 * data1 [7:0] $end
$var reg 8 + data2 [7:0] $end
$var reg 8 , data3 [7:0] $end
$var reg 8 - o_data [7:0] $end
$scope module u_click_three $end
$var wire 1 # i_rstn $end
$var wire 1 $ i_start $end
$var wire 1 . req $end
$var wire 1 / req_ack $end
$var wire 1 0 req3 $end
$var wire 1 1 req2 $end
$var wire 1 ' o_click3 $end
$var wire 1 ( o_click2 $end
$var wire 1 ) o_click1 $end
$var wire 1 2 ack3 $end
$var wire 1 3 ack2 $end
$var wire 1 4 ack1 $end
$var reg 1 5 req1 $end
$scope module u_click1 $end
$var wire 1 6 and_out $end
$var wire 1 5 i_reqL $end
$var wire 1 # i_rstn $end
$var wire 1 7 n_dff_outL $end
$var wire 1 8 n_dff_outR $end
$var wire 1 4 o_ackL $end
$var wire 1 ) o_click $end
$var wire 1 1 o_reqR $end
$var wire 1 9 xnor_out $end
$var wire 1 : xor_out $end
$var wire 1 3 i_ackR $end
$var wire 1 ; dff_outR $end
$var wire 1 < dff_outL $end
$scope module u_dffL $end
$var wire 1 6 i_clk $end
$var wire 1 7 i_d $end
$var wire 1 # i_rstn $end
$var wire 1 < o_q $end
$var reg 1 = q_internal $end
$upscope $end
$scope module u_dffR $end
$var wire 1 6 i_clk $end
$var wire 1 8 i_d $end
$var wire 1 # i_rstn $end
$var wire 1 ; o_q $end
$var reg 1 > q_internal $end
$upscope $end
$upscope $end
$scope module u_click2 $end
$var wire 1 ? and_out $end
$var wire 1 1 i_reqL $end
$var wire 1 # i_rstn $end
$var wire 1 @ n_dff_outL $end
$var wire 1 A n_dff_outR $end
$var wire 1 3 o_ackL $end
$var wire 1 ( o_click $end
$var wire 1 0 o_reqR $end
$var wire 1 B xnor_out $end
$var wire 1 C xor_out $end
$var wire 1 2 i_ackR $end
$var wire 1 D dff_outR $end
$var wire 1 E dff_outL $end
$scope module u_dffL $end
$var wire 1 ? i_clk $end
$var wire 1 @ i_d $end
$var wire 1 # i_rstn $end
$var wire 1 E o_q $end
$var reg 1 F q_internal $end
$upscope $end
$scope module u_dffR $end
$var wire 1 ? i_clk $end
$var wire 1 A i_d $end
$var wire 1 # i_rstn $end
$var wire 1 D o_q $end
$var reg 1 G q_internal $end
$upscope $end
$upscope $end
$scope module u_click3 $end
$var wire 1 H and_out $end
$var wire 1 / i_ackR $end
$var wire 1 0 i_reqL $end
$var wire 1 # i_rstn $end
$var wire 1 I n_dff_outL $end
$var wire 1 J n_dff_outR $end
$var wire 1 2 o_ackL $end
$var wire 1 ' o_click $end
$var wire 1 / o_reqR $end
$var wire 1 K xnor_out $end
$var wire 1 L xor_out $end
$var wire 1 M dff_outR $end
$var wire 1 N dff_outL $end
$scope module u_dffL $end
$var wire 1 H i_clk $end
$var wire 1 I i_d $end
$var wire 1 # i_rstn $end
$var wire 1 N o_q $end
$var reg 1 O q_internal $end
$upscope $end
$scope module u_dffR $end
$var wire 1 H i_clk $end
$var wire 1 J i_d $end
$var wire 1 # i_rstn $end
$var wire 1 M o_q $end
$var reg 1 P q_internal $end
$upscope $end
$upscope $end
$upscope $end
$upscope $end
$upscope $end
$enddefinitions $end
#0
$dumpvars
0P
0O
xN
xM
xL
xK
xJ
xI
xH
0G
0F
xE
xD
xC
xB
xA
x@
x?
0>
0=
x<
x;
x:
x9
x8
x7
x6
05
x4
x3
x2
x1
x0
x/
x.
b0 -
b0 ,
b0 +
b1111111 *
x)
x(
x'
b1111111 &
b101110001011110111011001100011011001000010111101110011011101000110000101100111011001010011001101011111011100000110100101110000011001010110010000101110011101100110001101100100 %
0$
0#
b1111111 "
b0 !
$end
#3000
04
0<
01
0;
03
0E
00
0D
02
0N
0/
0M
1.
#6000
17
18
1@
1A
1I
1J
#9000
0:
0C
0L
#12000
19
1B
1K
#13000
0)
06
0(
0?
0'
0H
#30000
15
1$
1#
#33000
0.
#36000
1:
#40000
b1111111 +
1>
1=
1)
16
#43000
05
11
1;
14
1<
#46000
1.
08
07
#49000
1C
#52000
09
#53000
b1111111 ,
1G
1F
1(
1?
#56000
10
1D
13
1E
0)
06
#59000
0A
0@
#62000
1L
0C
#65000
0B
19
#66000
b1111111 !
b1111111 -
1P
1O
1'
1H
0(
0?
#69000
0=
0>
1/
1M
12
1N
1)
16
#72000
15
04
0<
01
0;
0J
0I
#75000
0.
17
18
0L
#78000
1C
1B
#79000
0'
0H
#80000
b0 *
b0 "
b0 &
#81000
09
#82000
0F
0G
1(
1?
#85000
03
0E
00
0D
0)
06
#88000
1@
1A
#90000
b1 *
b1 "
b1 &
#91000
0C
1L
#94000
19
0B
#95000
0O
0P
0(
0?
1'
1H
#98000
b1 +
1>
1=
02
0N
0/
0M
1)
16
#100000
b10 *
b10 "
b10 &
#101000
05
11
1;
14
1<
1I
1J
#104000
1.
08
07
0L
#107000
1C
1B
#108000
0'
0H
#110000
b11 *
09
b11 "
b11 &
#111000
b1 ,
1G
1F
1(
1?
#114000
10
1D
13
1E
0)
06
#117000
0A
0@
#120000
b100 *
1L
0C
b100 "
b100 &
#123000
0B
19
#124000
b1 !
b1 -
1P
1O
1'
1H
0(
0?
#127000
b100 +
0=
0>
1/
1M
12
1N
1)
16
#130000
15
b101 *
04
0<
01
0;
0J
0I
b101 "
b101 &
#133000
0.
17
18
0L
#136000
1C
1B
#137000
0'
0H
#139000
09
#140000
b100 ,
0F
0G
b110 *
1(
1?
b110 "
b110 &
#143000
03
0E
00
0D
0)
06
#146000
1@
1A
#149000
0C
1L
#150000
b111 *
b111 "
b111 &
#152000
19
0B
#153000
b100 !
b100 -
0O
0P
0(
0?
1'
1H
#156000
b111 +
1>
1=
02
0N
0/
0M
1)
16
#159000
05
11
1;
14
1<
1I
1J
#160000
b1000 *
b1000 "
b1000 &
#162000
1.
08
07
0L
#165000
1C
1B
#166000
0'
0H
#168000
09
#169000
b111 ,
1G
1F
1(
1?
#172000
10
1D
13
1E
0)
06
#175000
0A
0@
#178000
1L
0C
#181000
0B
19
#182000
b111 !
b111 -
1P
1O
1'
1H
0(
0?
#185000
b1000 +
0=
0>
1/
1M
12
1N
1)
16
#188000
15
04
0<
01
0;
0J
0I
#191000
0.
17
18
0L
#194000
1C
1B
#195000
0'
0H
#197000
09
#198000
b1000 ,
0F
0G
1(
1?
#201000
03
0E
00
0D
0)
06
#204000
1@
1A
#207000
0C
1L
#210000
19
0B
#211000
b1000 !
b1000 -
0O
0P
0(
0?
1'
1H
#214000
1>
1=
02
0N
0/
0M
1)
16
#217000
05
11
1;
14
1<
1I
1J
#220000
1.
08
07
0L
#223000
1C
1B
#224000
0'
0H
#226000
09
#227000
1G
1F
1(
1?
#230000
10
1D
13
1E
0)
06
#233000
0A
0@
#236000
1L
0C
#239000
0B
19
#240000
1P
1O
1'
1H
0(
0?
#243000
0=
0>
1/
1M
12
1N
1)
16
#246000
15
04
0<
01
0;
0J
0I
#249000
0.
17
18
0L
#252000
1C
1B
#253000
0'
0H
#255000
09
#256000
0F
0G
1(
1?
#259000
03
0E
00
0D
0)
06
#262000
1@
1A
#265000
0C
1L
#268000
19
0B
#269000
0O
0P
0(
0?
1'
1H
#272000
1>
1=
02
0N
0/
0M
1)
16
#275000
05
11
1;
14
1<
1I
1J
#278000
1.
08
07
0L
#281000
1C
1B
#282000
0'
0H
#284000
09
#285000
1G
1F
1(
1?
#288000
10
1D
13
1E
0)
06
#291000
0A
0@
#294000
1L
0C
#297000
0B
19
#298000
1P
1O
1'
1H
0(
0?
#301000
0=
0>
1/
1M
12
1N
1)
16
#304000
15
04
0<
01
0;
0J
0I
#307000
0.
17
18
0L
#310000
1C
1B
#311000
0'
0H
#313000
09
#314000
0F
0G
1(
1?
#317000
03
0E
00
0D
0)
06
#320000
1@
1A
#323000
0C
1L
#326000
19
0B
#327000
0O
0P
0(
0?
1'
1H
#330000
1>
1=
02
0N
0/
0M
1)
16
#333000
05
11
1;
14
1<
1I
1J
#336000
1.
08
07
0L
#339000
1C
1B
#340000
0'
0H
#342000
09
#343000
1G
1F
1(
1?
#346000
10
1D
13
1E
0)
06
#349000
0A
0@
#352000
1L
0C
#355000
0B
19
#356000
1P
1O
1'
1H
0(
0?
#359000
0=
0>
1/
1M
12
1N
1)
16
#362000
15
04
0<
01
0;
0J
0I
#365000
0.
17
18
0L
#368000
1C
1B
#369000
0'
0H
#371000
09
#372000
0F
0G
1(
1?
#375000
03
0E
00
0D
0)
06
#378000
1@
1A
#381000
0C
1L
#384000
19
0B
#385000
0O
0P
0(
0?
1'
1H
#388000
1>
1=
02
0N
0/
0M
1)
16
#391000
05
11
1;
14
1<
1I
1J
#394000
1.
08
07
0L
#397000
1C
1B
#398000
0'
0H
#400000
09
#401000
1G
1F
1(
1?
#404000
10
1D
13
1E
0)
06
#407000
0A
0@
#410000
1L
0C
#413000
0B
19
#414000
1P
1O
1'
1H
0(
0?
#417000
0=
0>
1/
1M
12
1N
1)
16
#420000
15
04
0<
01
0;
0J
0I
#423000
0.
17
18
0L
#426000
1C
1B
#427000
0'
0H
#429000
09
#430000
0F
0G
1(
1?
#433000
03
0E
00
0D
0)
06
#436000
1@
1A
#439000
0C
1L
#442000
19
0B
#443000
0O
0P
0(
0?
1'
1H
#446000
1>
1=
02
0N
0/
0M
1)
16
#449000
05
11
1;
14
1<
1I
1J
#452000
1.
08
07
0L
#455000
1C
1B
#456000
0'
0H
#458000
09
#459000
1G
1F
1(
1?
#462000
10
1D
13
1E
0)
06
#465000
0A
0@
#468000
1L
0C
